MANIFEST.in
README.md
setup.py
bin/dragonfly-script.py
dragonfly/__init__.py
dragonfly/apis/__init__.py
dragonfly/apis/api_utils.py
dragonfly/apis/moo.py
dragonfly/apis/opt.py
dragonfly/distributions/__init__.py
dragonfly/distributions/continuous.py
dragonfly/distributions/discrete.py
dragonfly/distributions/distribution.py
dragonfly/distributions/model.py
dragonfly/distributions/product.py
dragonfly/distributions/unittest_continuous.py
dragonfly/distributions/unittest_discrete.py
dragonfly/distributions/unittest_metropolis.py
dragonfly/distributions/unittest_metropolis_discrete.py
dragonfly/distributions/unittest_nuts.py
dragonfly/distributions/unittest_posterior.py
dragonfly/distributions/unittest_posterior_mixed.py
dragonfly/distributions/unittest_product.py
dragonfly/distributions/unittest_slice.py
dragonfly/exd/__init__.py
dragonfly/exd/cp_domain_utils.py
dragonfly/exd/domains.py
dragonfly/exd/exd_core.py
dragonfly/exd/exd_utils.py
dragonfly/exd/experiment_caller.py
dragonfly/exd/unittest_cp_domain_utils.py
dragonfly/exd/unittest_domains.py
dragonfly/exd/unittest_exd_utils.py
dragonfly/exd/unittest_function_caller.py
dragonfly/exd/worker_manager.py
dragonfly/gp/__init__.py
dragonfly/gp/cartesian_product_gp.py
dragonfly/gp/euclidean_gp.py
dragonfly/gp/gp_core.py
dragonfly/gp/kernel.py
dragonfly/gp/mf_gp.py
dragonfly/gp/unittest_cartesian_product_gp.py
dragonfly/gp/unittest_euclidean_gp.py
dragonfly/gp/unittest_gp_core.py
dragonfly/gp/unittest_kernel.py
dragonfly/gp/unittest_mf_gp.py
dragonfly/nn/__init__.py
dragonfly/nn/neural_network.py
dragonfly/nn/nn_domains.py
dragonfly/nn/nn_examples.py
dragonfly/nn/nn_ga_optimiser.py
dragonfly/nn/nn_gp.py
dragonfly/nn/nn_modifiers.py
dragonfly/nn/nn_opt_utils.py
dragonfly/nn/nn_visualise.py
dragonfly/nn/otmann.py
dragonfly/nn/syn_nn_functions.py
dragonfly/nn/unittest_cp_nn_gp.py
dragonfly/nn/unittest_cp_nn_optimisers.py
dragonfly/nn/unittest_neural_network.py
dragonfly/nn/unittest_nn_domains.py
dragonfly_opt.egg-info/PKG-INFO
dragonfly_opt.egg-info/SOURCES.txt
dragonfly_opt.egg-info/dependency_links.txt
dragonfly_opt.egg-info/requires.txt
dragonfly_opt.egg-info/top_level.txt